<?xml version="1.0" encoding="UTF-8"?>
<ruleset>
    
    <!--The comment below is required by deliverance proxy.-->
    <!-- deliverance-proxy -->
    
    <match path="regex:.*/(emptypage|image_view_fullscreen|addcontentselector)$"
        abort="1" />
    <match path="regex:.*/(getContextSubMenu|translationbrowser_popup|manage_main)$"
        abort="1" />
    <match path="regex:.*/(table.htm|ploneimage.htm|anchor.htm|plonelink.htm)$"
        abort="1" />    
    <match path="regex:.*/(row.htm|cell.htm|pastetext.htm|source_editor.htm)$"
        abort="1" />
    <match path="regex:.*/(refbrowser_popup|@@updated_search)$"
        abort="1" />        
    <match path="regex:.*(.jpg|.png|.gif|.js|.css|.ico|.xml|.xsl)$" abort="1"/>
    <match path="regex:.*/(preview)$" abort="1" />                     
    <match environ="QUERY_STRING: wildcard:headless=*" abort="1" />      
    <match environ="QUERY_STRING: wildcard:transition_id=*" abort="1" />     
    <match path="regex:.*/(popup_change_workflow_state)$" abort="1" />
    <match path="regex:.*/(popout)$" abort="1" />
    <match path="/plone/" class="load-plone-navigation" />
    <match path="/exist/" class="load-exist-navigation" />    
    <match path="regex:^/(workspace|admin)/?"
        class="load-bungeni-navigation" />
    <match path="regex:^/(workspace)/?"
        class="load-workspace-navigation" />
    <match path="regex:^/(admin)/?"
        class="load-admin-navigation" />                        
    <match path="regex:^/(workspace/groups/my-groups)/?"
        class="load-workspace-group-navigation" />  
    <match path="regex:^/(plone/groups|plone/membership)/?"
        class="update-navigation" />               
    <match path="exact:/"
        class="frontpage" />
    <match path="exact:/front-page"
        class="frontpage" />
    <match path="/" class="primary" />
    
    <rule class="update-navigation">                    
        <pyquery pyref=
            "portal.theme.static.themes.rules:add_member_workspace_links"
        />  
        <prepend href="/"
            content="ul#portal-personaltools li.navigation"
            theme="children:#portal-globalnav ul.level1"/>
    </rule>
    
    <rule class="load-plone-navigation">        
        <!-- language selector -->
        <append content="//head"
                theme="children:/html/head"
                nocontent="ignore" />        
        <replace href="/"
            content="#portal-languageselector"
            theme="#portal-languageselector"/>   
        <drop content="ul#portal-personaltools li"
            if-content="not:.navigation"
        />                    
        <replace href="/"
            content="children:#portal-personaltools"
            theme="children:#portal-personaltools"/> 
        <drop theme="children:#portal-personaltools li.navigation" />
        <drop content="children:#personaltools-login" />
        <drop content="children:#user-name" /> 
        <drop content="children:#personaltools-logout" />

        <!-- navigation -->
        <prepend href="/"
            content="#portal-globalnav > li:first-child"
            theme="children:#portal-globalnav > ul" /> 
        <append href="/exist" content="#portal-globalnav > li"
            theme="children:#portal-globalnav > ul" />         
        <append content="#portal-globalnav > li:not(:first-child)"
            theme="children:#portal-globalnav > ul" />         
        <drop href="/plone"
            content="#portal-globalnav > li:first-child"/>           
        <drop theme="#processing_indicatron" />
        <prepend href="/plone"
            content="dl#footpanel"
            theme="#portal-footer"
        />            
    </rule>
    
    <rule class="load-exist-navigation">        
        
        <!-- navigation -->        
        <append content="#portal-globalnav > li"
            theme="children:#portal-globalnav > ul" />                   
        <drop href="/exist"
            content="#portal-globalnav > li:first-child"/>     
        <prepend href="/"
            content="#portal-globalnav > li:first-child"
            theme="children:#portal-globalnav > ul" />            
        <prepend content="ul#portal-personaltools li"
            theme="children:#portal-globalnav ul.level1" />      
     
        <!-- login link -->
        <append href="/"
                content="ul#portal-personaltools li:not(.navigation)"
                theme="children:#portal-personaltools"
        />        
        
        <append href="/plone" content="#portal-globalnav > li:not(:first-child)"
            theme="children:#portal-globalnav > ul" />
        <drop theme="#processing_indicatron" /> 
        <drop content="attributes(class):#portal-globalnav li:first-child" />
        <prepend href="/plone"
            content="dl#footpanel"
            theme="#portal-footer"
        />           
    </rule>    
    
    <rule class="load-workspace-navigation">    
        <prepend content="#portal-globalnav > li:first-child"
            theme="children:#portal-globalnav > ul" />    
        <pyquery pyref=
            "portal.theme.static.themes.rules:add_member_workspace_links"
        />          
    </rule>
    
    <rule class="load-admin-navigation">   
        <prepend content="#portal-globalnav > li:last-child"
            theme="children:#portal-globalnav > ul" />     
        <prepend content="#portal-globalnav > li:first-child"
            theme="children:#portal-globalnav > ul" />  
                        
    </rule>    
    
    <rule class="load-workspace-group-navigation" 
        pyref="portal.theme.static.themes.rules:redirect_group_workspace_links" >                
    </rule>
    
    <rule class="load-member-content">    
        <pyquery pyref=
            "portal.theme.static.themes.rules:add_member_public_links"
        />  
    </rule>                         
    
    
    <rule class="load-bungeni-navigation">              
        <append content="children:#portal-column-one"
            theme="children:#portal-column-one"
        />        
        <!-- navigation -->    
        <prepend href="/exist" content="#portal-globalnav > li"
            theme="children:#portal-globalnav > ul" />        
        <append href="/plone" content="#portal-globalnav > li:not(:first-child)"
            theme="children:#portal-globalnav ul.level0" />

        <prepend href="/plone"
            content="dl#footpanel"
            theme="#portal-footer"
        /> 

    </rule>    
    
    <rule class="frontpage">
        <append href="/plone"
                content="//head"
                theme="children:/html/head"
                nocontent="ignore" />                
        <replace content="#portal-logo" theme="#portal-logo" />
        <replace content="#portal-siteactions" theme="#portal-siteactions" />
        <drop href="/plone"
            content="#portal-breadcrumbs" />
        <drop content="#portal-search" />                      
        
        <!-- menu -->
        <drop href="/plone"
            content="#portal-globalnav > li:first-child"/>
        <drop href="/exist"
            content="#portal-globalnav > li:first-child"/>         
        <append href="/bungeni"
            content="#portal-globalnav > li:first-child"
            theme="children:#portal-globalnav > ul" />
        <append href="/exist" content="#portal-globalnav > li"
            theme="children:#portal-globalnav > ul" />          
        <append content="#portal-globalnav > li"
            theme="children:#portal-globalnav > ul" />
        <append href="/plone" content="#portal-globalnav > li:not(:first-child)"
            theme="children:#portal-globalnav > ul" />            
        <prepend href="/bungeni"
            content=".contentActions"
            theme="children:.main-content"
        />
        <drop content="#portal-column-content" />
        
        <replace content="#portal-personaltools" theme="#portal-personaltools" />
        <append href="/bungeni"
            content="ul#portal-personaltools li.navigation"
            theme="children:#portal-globalnav ul.level1"
        />
        
        <!--main content -->
        
        <replace href="/plone"
            content="#portal-column-content"
            theme="#portal-column-content" />
        
        <pyquery pyref=
            "portal.theme.static.themes.rules:add_menu_items"
        />
        <drop content="#portal-column-content" /> 
        
        <append href="/exist"
            content="ul#portal-personaltools li"
            theme="children:#portal-personaltools ul"
        />
        <prepend href="/plone"
            content="dl#footpanel"
            theme="#portal-footer"
        />    
    </rule>  
    
    
    <rule class="primary">
        <prepend content="//head/meta"
            theme="/html/head"
            nocontent="ignore" />
        <!-- menu -->
        <prepend content="#portal-globalnav > li"
            theme="children:#portal-globalnav > ul"
            if-content="not:base[href*='plone']"
        />
        <prepend content="ul#portal-personaltools li.navigation"
            theme="children:#portal-globalnav ul.level1"
            if-content=".navigation"
        />
        
        <append content="children:#portal-personaltools"
            theme="children:#portal-personaltools"
        />
        <pyquery pyref="portal.theme.static.themes.rules:image_links" />
        
        <!-- language selector -->
        <replace content="#portal-languageselector"
            theme="#portal-languageselector"
        />
        
        <!-- ui processing indicator -->
        <replace content="#processing_indicatron"
            theme="#processing_indicatron"
        />
        
        <pyquery pyref="portal.theme.static.themes.rules:replace_login_link"/>
        
        <!-- breadcrumbs -->
        <append content="children:#portal-breadcrumbs"
            theme="children:#portal-breadcrumbs"
        />
        
        <!-- workflow-popup -->
        <append content="children:#popup-load"
            theme="children:#popup-load"
        />          
        
        <!-- search -->
        <append content="children:#portal-search"
            theme="children:#portal-search"
        />
        
        <!-- Message info -->
        <replace content=".portalMessage"
            theme="children:.workspace_add_parliamentary_content"
        />     
        
        <!-- content -->
        <append content="children:#portal-column-content"
            theme="children:#portal-column-content"
        />
        
        <pyquery pyref=
            "portal.theme.static.themes.rules:reposition_contentActions"
        />      
        
        <!-- body attributes -->
        <append content="attributes:body" theme="attributes:body" />
        <pyquery pyref=
            "portal.theme.static.themes.rules:add_section_links"
        />
        <!--<pyquery pyref=
            "portal.theme.static.themes.rules:enable_text_editor"/>-->
        
    </rule>
</ruleset>

