<?xml version="1.0" encoding="utf-8"?>
<map>
	<mapresolver href="resources/maps/debaterecord/common/DebateRecordCommonMapResolver.xsl" />
	<elements>
		<element id="1" type="text:section" name="debaterecord" bungeniSectionType="debaterecord" result="debaterecord">
			<attribute attname="text:style-name" attresult="null" attvalue="null"/>
		</element>
		<element id="2" type="text:section" name="masthead" bungeniSectionType="MastHead" result="preface">
			<attribute attname="text:style-name" attresult="null" attvalue="null"/>
			<attribute attname="text:name" attresult="null" attvalue="null"/>
			<attribute attname="BungeniDebateOfficialDate" attresult="date" attvalue="BungeniDebateOfficialDate"/>
			<attribute attname="BungeniDebateOfficialTime" attresult="time" attvalue="BungeniDebateOfficialTime"/>
		</element>
		<element id="3" type="text:section" name="Observation" bungeniSectionType="Observation" result="comment"> 
			<attribute attname="text:style-name" attresult="null" attvalue="null"/>
			<attribute attname="text:name" attresult="null" attvalue="null"/>
			<attribute attname="BungeniQuestionsContainerType" attresult="type" attvalue="BungeniQuestionsContainerType"/>
			<attribute attname="BungeniQuestionNo" attresult="id" attvalue="BungeniQuestionNo"/>
			<attribute attname="BungeniQuestionBy" attresult="by" attvalue="BungeniQuestionBy"/>
			<attribute attname="BungeniQuestionTo" attresult="to" attvalue="BungeniQuestionTo"/>
			<attribute attname="BungeniQuestionStatus" attresult="status" attvalue="BungeniQuestionStatus"/>
		</element>
		<element id="4" type="text:section" name="GroupActivity" bungeniSectionType="GroupActivity" result="comment">
			<attribute attname="text:style-name" attresult="null" attvalue="null"/>
			<attribute attname="text:name" attresult="null" attvalue="null"/>
			<attribute attname="BungeniQuestionsContainerType" attresult="type" attvalue="BungeniQuestionsContainerType"/>
			<attribute attname="BungeniQuestionNo" attresult="id" attvalue="BungeniQuestionNo"/>
			<attribute attname="BungeniQuestionBy" attresult="by" attvalue="BungeniQuestionBy"/>
			<attribute attname="BungeniQuestionTo" attresult="to" attvalue="BungeniQuestionTo"/>
			<attribute attname="BungeniQuestionStatus" attresult="status" attvalue="BungeniQuestionStatus"/>
		</element>
 	    <element id="5" type="text:section" name="Speech" bungeniSectionType="Speech" result="Communication">
 	    	<attribute attname="text:style-name" attresult="null" attvalue="null"/>
			<attribute attname="text:name" attresult="null" attvalue="null"/>
			<attribute attname="BungeniQuestionsContainerType" attresult="type" attvalue="BungeniQuestionsContainerType"/>
			<attribute attname="BungeniQuestionNo" attresult="id" attvalue="BungeniQuestionNo"/>
			<attribute attname="BungeniQuestionBy" attresult="by" attvalue="BungeniQuestionBy"/>
			<attribute attname="BungeniQuestionTo" attresult="to" attvalue="BungeniQuestionTo"/>
			<attribute attname="BungeniQuestionStatus" attresult="status" attvalue="BungeniQuestionStatus"/>
		</element>
 		<element id="6" type="text:section" name="QuestionsContainer" bungeniSectionType="QuestionsContainer" result="subdivision">
			<attribute attname="text:style-name" attresult="null" attvalue="null"/>
			<attribute attname="text:name" attresult="null" attvalue="null"/>
			<attribute attname="BungeniQuestionsContainerType" attresult="type" attvalue="BungeniQuestionsContainerType"/>
			<attribute attname="BungeniQuestionNo" attresult="id" attvalue="BungeniQuestionNo"/>
			<attribute attname="BungeniQuestionBy" attresult="by" attvalue="BungeniQuestionBy"/>
			<attribute attname="BungeniQuestionTo" attresult="to" attvalue="BungeniQuestionTo"/>
			<attribute attname="BungeniQuestionStatus" attresult="status" attvalue="BungeniQuestionStatus"/>
		</element>
		<element id="7" type="text:section" name="QuestionAnswer" bungeniSectionType="QuestionAnswer" result="Questions">
			<attribute attname="text:style-name" attresult="null" attvalue="null"/>
			<attribute attname="text:name" attresult="null" attvalue="null"/>
			<attribute attname="BungeniQuestionsContainerType" attresult="type" attvalue="BungeniQuestionsContainerType"/>
			<attribute attname="BungeniQuestionNo" attresult="id" attvalue="BungeniQuestionNo"/>
			<attribute attname="BungeniQuestionBy" attresult="by" attvalue="BungeniQuestionBy"/>
			<attribute attname="BungeniQuestionTo" attresult="to" attvalue="BungeniQuestionTo"/>
			<attribute attname="BungeniQuestionStatus" attresult="status" attvalue="BungeniQuestionStatus"/>
		</element>
 		<element id="8" type="text:section" name="Question" bungeniSectionType="Question" result="question">
 			<attribute attname="text:style-name" attresult="null" attvalue="null"/>
			<attribute attname="text:name" attresult="null" attvalue="null"/>
			<attribute attname="BungeniQuestionsContainerType" attresult="type" attvalue="BungeniQuestionsContainerType"/>
			<attribute attname="BungeniQuestionNo" attresult="id" attvalue="BungeniQuestionNo"/>
			<attribute attname="BungeniQuestionBy" attresult="by" attvalue="BungeniQuestionBy"/>
			<attribute attname="BungeniQuestionTo" attresult="to" attvalue="BungeniQuestionTo"/>
			<attribute attname="BungeniQuestionStatus" attresult="status" attvalue="BungeniQuestionStatus"/>
		</element>
		<element id="9" type="text:section" name="PointOfOrder" bungeniSectionType="PointOfOrder" result="PointOfOrder">
			<attribute attname="text:style-name" attresult="null" attvalue="null"/>
			<attribute attname="text:name" attresult="null" attvalue="null"/>
			<attribute attname="BungeniQuestionsContainerType" attresult="type" attvalue="BungeniQuestionsContainerType"/>
			<attribute attname="BungeniQuestionNo" attresult="id" attvalue="BungeniQuestionNo"/>
			<attribute attname="BungeniQuestionBy" attresult="by" attvalue="BungeniQuestionBy"/>
			<attribute attname="BungeniQuestionTo" attresult="to" attvalue="BungeniQuestionTo"/>
			<attribute attname="BungeniQuestionStatus" attresult="status" attvalue="BungeniQuestionStatus"/>
		</element>
		<element id="10" type="text:section" name="ProceduralMotion" bungeniSectionType="ProceduralMotion" result="ProceduralMotions">
			<attribute attname="text:style-name" attresult="null" attvalue="null"/>
			<attribute attname="text:name" attresult="null" attvalue="null"/>
			<attribute attname="BungeniQuestionsContainerType" attresult="type" attvalue="BungeniQuestionsContainerType"/>
			<attribute attname="BungeniQuestionNo" attresult="id" attvalue="BungeniQuestionNo"/>
			<attribute attname="BungeniQuestionBy" attresult="by" attvalue="BungeniQuestionBy"/>
			<attribute attname="BungeniQuestionTo" attresult="to" attvalue="BungeniQuestionTo"/>
			<attribute attname="BungeniQuestionStatus" attresult="status" attvalue="BungeniQuestionStatus"/>
		</element>
		<element id="11" type="text:section" name="Person" bungeniSectionType="Person" result="from">
			<attribute attname="text:style-name" attresult="null" attvalue="null"/>
			<attribute attname="text:name" attresult="null" attvalue="null"/>
		</element>
		<element id="11" type="text:section" name="ActionEvent" bungeniSectionType="ActionEvent" result="subdivision">
			<attribute attname="text:style-name" attresult="null" attvalue="null"/>
			<attribute attname="text:name" attresult="null" attvalue="null"/>
		</element>
	</elements>
</map>